aegish/__init__.py
aegish/chatgpt.py
aegish/claude.py
aegish/commandrunner.py
aegish/config.py
aegish/debug.py
aegish/gemini.py
aegish/inputhandler.py
aegish/main.py
aegish/models.py
aegish/ollama.py
aegish/postprocess.py
aegish/safetychecker.py
aegish-0.1.0.dist-info/licenses/LICENSE
aegish-0.1.0.dist-info/METADATA
aegish-0.1.0.dist-info/WHEEL
aegish-0.1.0.dist-info/entry_points.txt
aegish-0.1.0.dist-info/top_level.txt
aegish-0.1.0.dist-info/RECORD
