Metadata-Version: 2.4
Name: aegish
Version: 0.1.0
Summary: Natural language to Linux command converter
Author: Zain Marshall
Author-email: Zain Marshall <zainmarshall1000@gmail.com>
License: MIT
Requires-Python: >=3.7
License-File: LICENSE
Requires-Dist: openai
Requires-Dist: google-genai
Requires-Dist: anthropic
Requires-Dist: ollama
Dynamic: author
Dynamic: license-file
